venture/__init__.py
venture/app.py
venture/casual_utils.py
venture/config.py
venture/metadata.py
venture/logic/__init__.py
venture/logic/cosmos_logic.py
venture/logic/explore_logic.py
venture/logic/function_name_logic.py
venture/logic/interlink_logic.py
venture/logic/json_fixer_logic.py
venture/logic/loaders_logic.py
venture/logic/model_selector_logic.py
venture/logic/openai_logic.py
venture/logic/token_count_logic.py
venture/logic/retrieval_logic/__init__.py
venture/logic/retrieval_logic/retrieval_logic.py
venture/logic/retrieval_logic/objects/__init__.py
venture/logic/retrieval_logic/objects/package_input.py
venture/logic/retrieval_logic/objects/package_output.py
venture/logic/retrieval_logic/objects/retrieval_output.py
venture/objects/__init__.py
venture/objects/chat_gpt_output.py
venture/objects/context_based_response_output.py
venture/objects/file_type.py
venture/objects/interlink_commander_details_output.py
venture/objects/llm_output.py
venture/objects/parse_result.py
venture/objects/parsed_doc.py
venture/objects/token_counts.py
venture/prompts/__init__.py
venture/prompts/system_function_name.py
venture/prompts/system_ownership.py
venture/prompts/system_retrieval_caller.py
venture/prompts/system_retrieval_verdict.py
venture/prompts/system_summary.py
venture/prompts/system_venture.py
venture_ai-0.9.9.dist-info/LICENSE
venture_ai-0.9.9.dist-info/METADATA
venture_ai-0.9.9.dist-info/WHEEL
venture_ai-0.9.9.dist-info/top_level.txt
venture_ai-0.9.9.dist-info/RECORD
