Metadata-Version: 2.1
Name: venture-ai
Version: 0.9.9
Summary: A Fast, Flexible Trainer with Callbacks and Extensions for PyTorch
Home-page: https://github.com/roysadaka/venture
Author: Roy Sadaka
Maintainer: lpd developers
Maintainer-email: torch.lpd@gmail.com
License: MIT Licences
Keywords: ai,natural language processing,large language models,project exploration,chatbot,documentation exploration,reasoning based search,assistant,chatgpt,openai
Classifier: Development Status :: 4 - Beta
Classifier: Intended Audience :: Developers
Classifier: Intended Audience :: Education
Classifier: License :: OSI Approved :: Apache Software License
Classifier: Operating System :: OS Independent
Classifier: Programming Language :: Python :: 3
Classifier: Programming Language :: Python :: 3.9
Classifier: Topic :: Scientific/Engineering :: Artificial Intelligence
Classifier: Topic :: Utilities
Requires-Python: >=3.9
License-File: LICENSE
Requires-Dist: gradio
Requires-Dist: docx2txt
Requires-Dist: pdf2docx
Requires-Dist: openai
Requires-Dist: tiktoken
